{
    "\u4e61\u6751\u7231\u60c511": [
        {
            "name": "0-\u4e61\u6751\u7231\u60c511\u8fde\u8f7d\u81f357\u96c6",
            "action": "ftp://g:g@tv.kaida365.com:2166/\u4e61\u6751\u7231\u60c511-02.mp4"
        },
        {
            "name": "1-\u4e61\u6751\u7231\u60c511\u8fde\u8f7d\u81f357\u96c6",
            "action": "ftp://g:g@tv.kaida365.com:2166/\u4e61\u6751\u7231\u60c511-03.mp4"
        },
        {
            "name": "2-\u4e61\u6751\u7231\u60c511\u8fde\u8f7d\u81f357\u96c6",
            "action": "ftp://g:g@tv.kaida365.com:2166/\u4e61\u6751\u7231\u60c511-04.mp4"
        },
        {
            "name": "3-\u4e61\u6751\u7231\u60c511\u8fde\u8f7d\u81f357\u96c6",
            "action": "ftp://g:g@tv.kaida365.com:2166/\u4e61\u6751\u7231\u60c511-05.mp4"
        },
        {
            "name": "4-\u4e61\u6751\u7231\u60c511\u8fde\u8f7d\u81f357\u96c6",
            "action": "ftp://g:g@tv.kaida365.com:2166/\u4e61\u6751\u7231\u60c511-06.mp4"
        },
        {
            "name": "5-\u4e61\u6751\u7231\u60c511\u8fde\u8f7d\u81f357\u96c6",
            "action": "ftp://g:g@tv.kaida365.com:2166/\u4e61\u6751\u7231\u60c511-07.mp4"
        },
        {
            "name": "6-\u4e61\u6751\u7231\u60c511\u8fde\u8f7d\u81f357\u96c6",
            "action": "ftp://g:g@tv.kaida365.com:2166/\u4e61\u6751\u7231\u60c511-08.mp4"
        },
        {
            "name": "7-\u4e61\u6751\u7231\u60c511\u8fde\u8f7d\u81f357\u96c6",
            "action": "ftp://g:g@tv.kaida365.com:2166/\u4e61\u6751\u7231\u60c511-09.mp4"
        },
        {
            "name": "8-\u4e61\u6751\u7231\u60c511\u8fde\u8f7d\u81f357\u96c6",
            "action": "ftp://g:g@tv.kaida365.com:2166/\u4e61\u6751\u7231\u60c511-10.mp4"
        },
        {
            "name": "9-\u4e61\u6751\u7231\u60c511\u8fde\u8f7d\u81f357\u96c6",
            "action": "ftp://g:g@tv.kaida365.com:2166/\u4e61\u6751\u7231\u60c511-11.mp4"
        },
        {
            "name": "10-\u4e61\u6751\u7231\u60c511\u8fde\u8f7d\u81f357\u96c6",
            "action": "ftp://g:g@tv.kaida365.com:2166/\u4e61\u6751\u7231\u60c511-12.mp4"
        },
        {
            "name": "11-\u4e61\u6751\u7231\u60c511\u8fde\u8f7d\u81f357\u96c6",
            "action": "ftp://g:g@tv.kaida365.com:2166/\u4e61\u6751\u7231\u60c511-13.mp4"
        },
        {
            "name": "12-\u4e61\u6751\u7231\u60c511\u8fde\u8f7d\u81f357\u96c6",
            "action": "ftp://g:g@tv.kaida365.com:2166/\u4e61\u6751\u7231\u60c511-14.mp4"
        },
        {
            "name": "13-\u4e61\u6751\u7231\u60c511\u8fde\u8f7d\u81f357\u96c6",
            "action": "ftp://g:g@tv.kaida365.com:2166/\u4e61\u6751\u7231\u60c511-15.mp4"
        },
        {
            "name": "14-\u4e61\u6751\u7231\u60c511\u8fde\u8f7d\u81f357\u96c6",
            "action": "ftp://g:g@tv.kaida365.com:2166/\u4e61\u6751\u7231\u60c511-16.mp4"
        },
        {
            "name": "15-\u4e61\u6751\u7231\u60c511\u8fde\u8f7d\u81f357\u96c6",
            "action": "ftp://g:g@tv.kaida365.com:2166/\u4e61\u6751\u7231\u60c511-17.mp4"
        },
        {
            "name": "16-\u4e61\u6751\u7231\u60c511\u8fde\u8f7d\u81f357\u96c6",
            "action": "ftp://g:g@tv.kaida365.com:2166/\u4e61\u6751\u7231\u60c511-18.mp4"
        },
        {
            "name": "17-\u4e61\u6751\u7231\u60c511\u8fde\u8f7d\u81f357\u96c6",
            "action": "ftp://g:g@tv.kaida365.com:2166/\u4e61\u6751\u7231\u60c511-19.mp4"
        },
        {
            "name": "18-\u4e61\u6751\u7231\u60c511\u8fde\u8f7d\u81f357\u96c6",
            "action": "ftp://g:g@tv.kaida365.com:2166/\u4e61\u6751\u7231\u60c511-20.mp4"
        },
        {
            "name": "19-\u4e61\u6751\u7231\u60c511\u8fde\u8f7d\u81f357\u96c6",
            "action": "ftp://g:g@tv.kaida365.com:2166/\u4e61\u6751\u7231\u60c511-21.mp4"
        },
        {
            "name": "20-\u4e61\u6751\u7231\u60c511\u8fde\u8f7d\u81f357\u96c6",
            "action": "ftp://g:g@tv.kaida365.com:2166/\u4e61\u6751\u7231\u60c511-22.mp4"
        },
        {
            "name": "21-\u4e61\u6751\u7231\u60c511\u8fde\u8f7d\u81f357\u96c6",
            "action": "ftp://g:g@tv.kaida365.com:2166/\u4e61\u6751\u7231\u60c511-23.mp4"
        },
        {
            "name": "22-\u4e61\u6751\u7231\u60c511\u8fde\u8f7d\u81f357\u96c6",
            "action": "ftp://g:g@tv.kaida365.com:2166/\u4e61\u6751\u7231\u60c511-24.mp4"
        },
        {
            "name": "23-\u4e61\u6751\u7231\u60c511\u8fde\u8f7d\u81f357\u96c6",
            "action": "ftp://g:g@tv.kaida365.com:2166/\u4e61\u6751\u7231\u60c511-25.mp4"
        },
        {
            "name": "24-\u4e61\u6751\u7231\u60c511\u8fde\u8f7d\u81f357\u96c6",
            "action": "ftp://g:g@tv.kaida365.com:2166/\u4e61\u6751\u7231\u60c511-26.mp4"
        },
        {
            "name": "25-\u4e61\u6751\u7231\u60c511\u8fde\u8f7d\u81f357\u96c6",
            "action": "ftp://g:g@tv.kaida365.com:2166/\u4e61\u6751\u7231\u60c511-27.mp4"
        },
        {
            "name": "26-\u4e61\u6751\u7231\u60c511\u8fde\u8f7d\u81f357\u96c6",
            "action": "ftp://g:g@tv.kaida365.com:2166/\u4e61\u6751\u7231\u60c511-28.mp4"
        },
        {
            "name": "27-\u4e61\u6751\u7231\u60c511\u8fde\u8f7d\u81f357\u96c6",
            "action": "ftp://g:g@tv.kaida365.com:2166/\u4e61\u6751\u7231\u60c511-29.mp4"
        },
        {
            "name": "28-\u4e61\u6751\u7231\u60c511\u8fde\u8f7d\u81f357\u96c6",
            "action": "ftp://g:g@tv.kaida365.com:2166/\u4e61\u6751\u7231\u60c511-30.mp4"
        },
        {
            "name": "29-\u4e61\u6751\u7231\u60c511\u8fde\u8f7d\u81f357\u96c6",
            "action": "ftp://g:g@tv.kaida365.com:2166/\u4e61\u6751\u7231\u60c511-31.mp4"
        },
        {
            "name": "30-\u4e61\u6751\u7231\u60c511\u8fde\u8f7d\u81f357\u96c6",
            "action": "ftp://g:g@tv.kaida365.com:2166/\u4e61\u6751\u7231\u60c511-32.mp4"
        },
        {
            "name": "31-\u4e61\u6751\u7231\u60c511\u8fde\u8f7d\u81f357\u96c6",
            "action": "ftp://g:g@tv.kaida365.com:2166/\u4e61\u6751\u7231\u60c511-33.mp4"
        },
        {
            "name": "32-\u4e61\u6751\u7231\u60c511\u8fde\u8f7d\u81f357\u96c6",
            "action": "ftp://g:g@tv.kaida365.com:2166/\u4e61\u6751\u7231\u60c511-34.mp4"
        },
        {
            "name": "33-\u4e61\u6751\u7231\u60c511\u8fde\u8f7d\u81f357\u96c6",
            "action": "ftp://g:g@tv.kaida365.com:2166/\u4e61\u6751\u7231\u60c511-35.mp4"
        },
        {
            "name": "34-\u4e61\u6751\u7231\u60c511\u8fde\u8f7d\u81f357\u96c6",
            "action": "ftp://g:g@tv.kaida365.com:2166/\u4e61\u6751\u7231\u60c511-36.mp4"
        },
        {
            "name": "35-\u4e61\u6751\u7231\u60c511\u8fde\u8f7d\u81f357\u96c6",
            "action": "ftp://g:g@tv.kaida365.com:2166/\u4e61\u6751\u7231\u60c511-37.mp4"
        },
        {
            "name": "36-\u4e61\u6751\u7231\u60c511\u8fde\u8f7d\u81f357\u96c6",
            "action": "ftp://g:g@tv.kaida365.com:2166/\u4e61\u6751\u7231\u60c511-38.mp4"
        },
        {
            "name": "37-\u4e61\u6751\u7231\u60c511\u8fde\u8f7d\u81f357\u96c6",
            "action": "ftp://g:g@tv.kaida365.com:2166/\u4e61\u6751\u7231\u60c511-39.mp4"
        },
        {
            "name": "38-\u4e61\u6751\u7231\u60c511\u8fde\u8f7d\u81f357\u96c6",
            "action": "ftp://g:g@tv.kaida365.com:2166/\u4e61\u6751\u7231\u60c511-40.mp4"
        },
        {
            "name": "39-\u4e61\u6751\u7231\u60c511\u8fde\u8f7d\u81f357\u96c6",
            "action": "ftp://g:g@tv.kaida365.com:2166/\u4e61\u6751\u7231\u60c511-41.mp4"
        },
        {
            "name": "40-\u4e61\u6751\u7231\u60c511\u8fde\u8f7d\u81f357\u96c6",
            "action": "ftp://g:g@tv.kaida365.com:2166/\u4e61\u6751\u7231\u60c511-42.mp4"
        },
        {
            "name": "41-\u4e61\u6751\u7231\u60c511\u8fde\u8f7d\u81f357\u96c6",
            "action": "ftp://g:g@tv.kaida365.com:2166/\u4e61\u6751\u7231\u60c511-43.mp4"
        },
        {
            "name": "42-\u4e61\u6751\u7231\u60c511\u8fde\u8f7d\u81f357\u96c6",
            "action": "ftp://g:g@tv.kaida365.com:2166/\u4e61\u6751\u7231\u60c511-44.mp4"
        },
        {
            "name": "43-\u4e61\u6751\u7231\u60c511\u8fde\u8f7d\u81f357\u96c6",
            "action": "ftp://g:g@tv.kaida365.com:2166/\u4e61\u6751\u7231\u60c511-45.mp4"
        },
        {
            "name": "44-\u4e61\u6751\u7231\u60c511\u8fde\u8f7d\u81f357\u96c6",
            "action": "ftp://g:g@tv.kaida365.com:2166/\u4e61\u6751\u7231\u60c511-46.mp4"
        },
        {
            "name": "45-\u4e61\u6751\u7231\u60c511\u8fde\u8f7d\u81f357\u96c6",
            "action": "ftp://g:g@tv.kaida365.com:2166/\u4e61\u6751\u7231\u60c511-47.mp4"
        },
        {
            "name": "46-\u4e61\u6751\u7231\u60c511\u8fde\u8f7d\u81f357\u96c6",
            "action": "ftp://g:g@tv.kaida365.com:2166/\u4e61\u6751\u7231\u60c511-48.mp4"
        },
        {
            "name": "47-\u4e61\u6751\u7231\u60c511\u8fde\u8f7d\u81f357\u96c6",
            "action": "ftp://g:g@tv.kaida365.com:2166/\u4e61\u6751\u7231\u60c511-49.mp4"
        },
        {
            "name": "48-\u4e61\u6751\u7231\u60c511\u8fde\u8f7d\u81f357\u96c6",
            "action": "ftp://g:g@tv.kaida365.com:2166/\u4e61\u6751\u7231\u60c511-50.mp4"
        },
        {
            "name": "49-\u4e61\u6751\u7231\u60c511\u8fde\u8f7d\u81f357\u96c6",
            "action": "ftp://g:g@tv.kaida365.com:2166/\u4e61\u6751\u7231\u60c511-51.mp4"
        },
        {
            "name": "50-\u4e61\u6751\u7231\u60c511\u8fde\u8f7d\u81f357\u96c6",
            "action": "ftp://g:g@tv.kaida365.com:2166/\u4e61\u6751\u7231\u60c511-52.mp4"
        },
        {
            "name": "51-\u4e61\u6751\u7231\u60c511\u8fde\u8f7d\u81f357\u96c6",
            "action": "ftp://g:g@tv.kaida365.com:2166/\u4e61\u6751\u7231\u60c511-53.mp4"
        },
        {
            "name": "52-\u4e61\u6751\u7231\u60c511\u8fde\u8f7d\u81f357\u96c6",
            "action": "ftp://g:g@tv.kaida365.com:2166/\u4e61\u6751\u7231\u60c511-54.mp4"
        },
        {
            "name": "53-\u4e61\u6751\u7231\u60c511\u8fde\u8f7d\u81f357\u96c6",
            "action": "ftp://g:g@tv.kaida365.com:2166/\u4e61\u6751\u7231\u60c511-55.mp4"
        },
        {
            "name": "54-\u4e61\u6751\u7231\u60c511\u8fde\u8f7d\u81f357\u96c6",
            "action": "ftp://g:g@tv.kaida365.com:2166/\u4e61\u6751\u7231\u60c511-56.mp4"
        },
        {
            "name": "55-\u4e61\u6751\u7231\u60c511\u8fde\u8f7d\u81f357\u96c6",
            "action": "ftp://g:g@tv.kaida365.com:2166/\u4e61\u6751\u7231\u60c511-57.mp4"
        }
    ]
}