{
    "\u56fd\u52a1\u537f\u5973\u58eb \u7b2c\u4e94\u5b63": [
        {
            "name": "0-\u56fd\u52a1\u537f\u5973\u58eb \u7b2c\u4e94\u5b63\u8fde\u8f7d\u81f314\u96c6",
            "action": "ftp://m:m@tv.kaida365.com:2199/\u56fd\u52a1\u537f\u5973\u58eb\u7b2c\u4e94\u5b6302.mkv"
        },
        {
            "name": "1-\u56fd\u52a1\u537f\u5973\u58eb \u7b2c\u4e94\u5b63\u8fde\u8f7d\u81f314\u96c6",
            "action": "ftp://m:m@tv.kaida365.com:2199/\u56fd\u52a1\u537f\u5973\u58eb\u7b2c\u4e94\u5b6303.mp4"
        },
        {
            "name": "2-\u56fd\u52a1\u537f\u5973\u58eb \u7b2c\u4e94\u5b63\u8fde\u8f7d\u81f314\u96c6",
            "action": "ftp://m:m@tv.kaida365.com:2199/\u56fd\u52a1\u537f\u5973\u58eb\u7b2c\u4e94\u5b6304.mp4"
        },
        {
            "name": "3-\u56fd\u52a1\u537f\u5973\u58eb \u7b2c\u4e94\u5b63\u8fde\u8f7d\u81f314\u96c6",
            "action": "ftp://m:m@tv.kaida365.com:2199/\u56fd\u52a1\u537f\u5973\u58eb\u7b2c\u4e94\u5b6305.mp4"
        },
        {
            "name": "4-\u56fd\u52a1\u537f\u5973\u58eb \u7b2c\u4e94\u5b63\u8fde\u8f7d\u81f314\u96c6",
            "action": "ftp://m:m@tv.kaida365.com:2199/\u56fd\u52a1\u537f\u5973\u58eb\u7b2c\u4e94\u5b6306.mp4"
        },
        {
            "name": "5-\u56fd\u52a1\u537f\u5973\u58eb \u7b2c\u4e94\u5b63\u8fde\u8f7d\u81f314\u96c6",
            "action": "ftp://m:m@tv.kaida365.com:2199/\u56fd\u52a1\u537f\u5973\u58eb\u7b2c\u4e94\u5b6307.mp4"
        },
        {
            "name": "6-\u56fd\u52a1\u537f\u5973\u58eb \u7b2c\u4e94\u5b63\u8fde\u8f7d\u81f314\u96c6",
            "action": "ftp://m:m@tv.kaida365.com:2199/\u56fd\u52a1\u537f\u5973\u58eb\u7b2c\u4e94\u5b6308.mp4"
        },
        {
            "name": "7-\u56fd\u52a1\u537f\u5973\u58eb \u7b2c\u4e94\u5b63\u8fde\u8f7d\u81f314\u96c6",
            "action": "ftp://m:m@tv.kaida365.com:2199/\u56fd\u52a1\u537f\u5973\u58eb\u7b2c\u4e94\u5b6309.mp4"
        },
        {
            "name": "8-\u56fd\u52a1\u537f\u5973\u58eb \u7b2c\u4e94\u5b63\u8fde\u8f7d\u81f314\u96c6",
            "action": "ftp://m:m@tv.kaida365.com:2199/\u56fd\u52a1\u537f\u5973\u58eb\u7b2c\u4e94\u5b6310.mp4"
        },
        {
            "name": "9-\u56fd\u52a1\u537f\u5973\u58eb \u7b2c\u4e94\u5b63\u8fde\u8f7d\u81f314\u96c6",
            "action": "ftp://m:m@tv.kaida365.com:2199/\u56fd\u52a1\u537f\u5973\u58eb\u7b2c\u4e94\u5b6311.mp4"
        },
        {
            "name": "10-\u56fd\u52a1\u537f\u5973\u58eb \u7b2c\u4e94\u5b63\u8fde\u8f7d\u81f314\u96c6",
            "action": "ftp://m:m@tv.kaida365.com:2199/\u56fd\u52a1\u537f\u5973\u58eb\u7b2c\u4e94\u5b6312.mp4"
        },
        {
            "name": "11-\u56fd\u52a1\u537f\u5973\u58eb \u7b2c\u4e94\u5b63\u8fde\u8f7d\u81f314\u96c6",
            "action": "ftp://m:m@tv.kaida365.com:2199/\u56fd\u52a1\u537f\u5973\u58eb\u7b2c\u4e94\u5b6313.mp4"
        },
        {
            "name": "12-\u56fd\u52a1\u537f\u5973\u58eb \u7b2c\u4e94\u5b63\u8fde\u8f7d\u81f314\u96c6",
            "action": "ftp://m:m@tv.kaida365.com:2199/\u56fd\u52a1\u537f\u5973\u58eb\u7b2c\u4e94\u5b6314.mp4"
        }
    ]
}