{
    "\u4e2d\u56fd\u8bd7\u8bcd\u5927\u4f1a \u7b2c\u4e09\u5b63": [
        {
            "name": "[  \u8bd7\u8bcd\u5927\u4f1a \u7b2c\u4e09\u5b63][\u516810\u671f][[\u8f6c\u8f7d\u6807\u6ce8\u51fa\u5904][cyw]",
            "action": "magnet:?xt=urn:btih:7404c378d8e233fb2e47496696fbce13a9b59831&dn=%5B%E4%B8%AD%E5%9B%BD%E8%AF%97%E8%AF%8D%E5%A4%A7%E4%BC%9A%20%E7%AC%AC%E4%B8%89%E5%AD%A3%5D%5B%E5%85%A810%E6%9C%9F%5D%5B%5B%E8%BD%AC%E8%BD%BD%E6%A0%87%E6%B3%A8%E5%87%BA%E5%A4%84%5D%5BCYW%5D"
        },
        {
            "name": "[  \u8bd7\u8bcd\u5927\u4f1a.\u7b2c\u4e09\u5b63][10\u671f\u5168][imp4ba]",
            "action": "magnet:?xt=urn:btih:9bfd77f4204e21fd94d5e15e4680bf87ce14ea14&dn=%5B%E4%B8%AD%E5%9B%BD%E8%AF%97%E8%AF%8D%E5%A4%A7%E4%BC%9A.%E7%AC%AC%E4%B8%89%E5%AD%A3%5D%5B10%E6%9C%9F%E5%85%A8%5D%5BIMP4BA%5D"
        },
        {
            "name": "chinese.poetry.conference.s03.ep03.hd-720p.x2  .aac.manda  n.chs-52movieba",
            "action": "magnet:?xt=urn:btih:559d8064cee7f4ac48a8fd474186b2a9af8726b5&dn=Chinese.Poetry.Conference.S03.EP03.HD-720P.X264.AAC.Mandarin.CHS-52movieba"
        },
        {
            "name": "chinese.poetry.conference.s03.ep03.hd-1080p.x2  .aac.manda  n.chs-52movieba",
            "action": "magnet:?xt=urn:btih:8d2ebf05afc608da24325b868fda84476d7d62a7&dn=Chinese.Poetry.Conference.S03.EP03.HD-1080P.X264.AAC.Mandarin.CHS-52movieba"
        },
        {
            "name": "chinese.poetry.conference.s03.ep09.hd-720p.x2  .aac.manda  n.chs-52movieba",
            "action": "magnet:?xt=urn:btih:158c8f5ae435871ecb5353a304c2944f734ca0d7&dn=Chinese.Poetry.Conference.S03.EP09.HD-720P.X264.AAC.Mandarin.CHS-52movieba"
        },
        {
            "name": "chinese.poetry.conference.s03.ep02.hd-720p.x2  .aac.manda  n.chs-52movieba",
            "action": "magnet:?xt=urn:btih:1df70142e45e187c552e18c8d776ea915bcb54bd&dn=Chinese.Poetry.Conference.S03.EP02.HD-720P.X264.AAC.Mandarin.CHS-52movieba"
        },
        {
            "name": "chinese.poetry.conference.s03.ep04.hd-720p.x2  .aac.manda  n.chs-52movieba",
            "action": "magnet:?xt=urn:btih:27703471cbdd0a13df6efbdd5792f3b2204eecf1&dn=Chinese.Poetry.Conference.S03.EP04.HD-720P.X264.AAC.Mandarin.CHS-52movieba"
        },
        {
            "name": "chinese.poetry.conference.s03.ep01.hd-720p.x2  .aac.manda  n.chs-52movieba",
            "action": "magnet:?xt=urn:btih:2aa63ddc5f70e0de2efa456cfcbc07ce27be03f5&dn=Chinese.Poetry.Conference.S03.EP01.HD-720P.X264.AAC.Mandarin.CHS-52movieba"
        },
        {
            "name": "chinese.poetry.conference.s03.ep10.hd-1080p.x2  .aac.manda  n.chs-52movieba",
            "action": "magnet:?xt=urn:btih:561b22b18f7ec0af17a7c216c3ea644413517768&dn=Chinese.Poetry.Conference.S03.EP10.HD-1080P.X264.AAC.Mandarin.CHS-52movieba"
        },
        {
            "name": "chinese.poetry.conference.s03.ep08.hd-720p.x2  .aac.manda  n.chs-52movieba",
            "action": "magnet:?xt=urn:btih:57e8631268160603083a571ec178e57dee5d0c18&dn=Chinese.Poetry.Conference.S03.EP08.HD-720P.X264.AAC.Mandarin.CHS-52movieba"
        },
        {
            "name": "chinese.poetry.conference.s03.ep06.hd-720p.x2  .aac.manda  n.chs-52movieba",
            "action": "magnet:?xt=urn:btih:68faae9387a56d43fa19300783ff8e69b2197332&dn=Chinese.Poetry.Conference.S03.EP06.HD-720P.X264.AAC.Mandarin.CHS-52movieba"
        },
        {
            "name": "chinese.poetry.conference.s03.ep09.hd-1080p.x2  .aac.manda  n.chs-52movieba",
            "action": "magnet:?xt=urn:btih:6caff9023229cbfa118a6a985e2e2cbd3f713423&dn=Chinese.Poetry.Conference.S03.EP09.HD-1080P.X264.AAC.Mandarin.CHS-52movieba"
        },
        {
            "name": "chinese.poetry.conference.s03.ep02.hd-1080p.x2  .aac.manda  n.chs-52movieba",
            "action": "magnet:?xt=urn:btih:780c950d5498df0a09f5e141c931499ed85da39d&dn=Chinese.Poetry.Conference.S03.EP02.HD-1080P.X264.AAC.Mandarin.CHS-52movieba"
        },
        {
            "name": "chinese.poetry.conference.s03.ep06.hd-1080p.x2  .aac.manda  n.chs-52movieba",
            "action": "magnet:?xt=urn:btih:80721fd3c8323a2f94f27527826400f0a15ee243&dn=Chinese.Poetry.Conference.S03.EP06.HD-1080P.X264.AAC.Mandarin.CHS-52movieba"
        },
        {
            "name": "chinese.poetry.conference.s03.ep05.hd-1080p.x2  .aac.manda  n.chs-52movieba",
            "action": "magnet:?xt=urn:btih:8191b6e4b12e48d0f77681dcb447b45a36702471&dn=Chinese.Poetry.Conference.S03.EP05.HD-1080P.X264.AAC.Mandarin.CHS-52movieba"
        },
        {
            "name": "chinese.poetry.conference.s03.ep08.hd-1080p.x2  .aac.manda  n.chs-52movieba",
            "action": "magnet:?xt=urn:btih:903667fa85c4724b1680f3ec77bc655cd4558d4d&dn=Chinese.Poetry.Conference.S03.EP08.HD-1080P.X264.AAC.Mandarin.CHS-52movieba"
        },
        {
            "name": "chinese.poetry.conference.s03.ep10.hd-720p.x2  .aac.manda  n.chs-52movieba",
            "action": "magnet:?xt=urn:btih:91ad1209ad77e4d8efffb207c719afd7624b6fda&dn=Chinese.Poetry.Conference.S03.EP10.HD-720P.X264.AAC.Mandarin.CHS-52movieba"
        },
        {
            "name": "chinese.poetry.conference.s03.ep07.hd-720p.x2  .aac.manda  n.chs-52movieba",
            "action": "magnet:?xt=urn:btih:a6f943d0dcc5f9e829e1e42733d3ed5f9f10e3a5&dn=Chinese.Poetry.Conference.S03.EP07.HD-720P.X264.AAC.Mandarin.CHS-52movieba"
        },
        {
            "name": "chinese.poetry.conference.s03.ep01.hd-1080p.x2  .aac.manda  n.chs-52movieba",
            "action": "magnet:?xt=urn:btih:cfe089ae5348179dc324cb79fdb8090ef4272574&dn=Chinese.Poetry.Conference.S03.EP01.HD-1080P.X264.AAC.Mandarin.CHS-52movieba"
        },
        {
            "name": "chinese.poetry.conference.s03.ep05.hd-720p.x2  .aac.manda  n.chs-52movieba",
            "action": "magnet:?xt=urn:btih:ddb19de759b2296a4c8f22d77e66644f2109da6e&dn=Chinese.Poetry.Conference.S03.EP05.HD-720P.X264.AAC.Mandarin.CHS-52movieba"
        }
    ]
}