{
    "\u547d\u8fd0\u4e0e\u6124\u6012": [
        {
            "name": "www.tskscn.com(\u547d\u8fd0\u4e0e\u6124\u6012)",
            "action": "magnet:?xt=urn:btih:0269fb4a4e50b5e66577b5359ced81520f3c19b2&dn=www.tskscn.com%28%E5%91%BD%E8%BF%90%E4%B8%8E%E6%84%A4%E6%80%92%29"
        },
        {
            "name": "[\u97e9\u8ff7\u5b57\u5e55\u7ec4www.hanmi520.com][\u547d\u8fd0\u4e0e\u6124\u6012][\u7b2c13-14\u96c6][\u97e9\u8bed\u4e2d\u5b57][720p].mp4",
            "action": "magnet:?xt=urn:btih:0357057039e1d0b8384ae6c412294289fc674689&dn=%5B%E9%9F%A9%E8%BF%B7%E5%AD%97%E5%B9%95%E7%BB%84www.hanmi520.com%5D%5B%E5%91%BD%E8%BF%90%E4%B8%8E%E6%84%A4%E6%80%92%5D%5B%E7%AC%AC13-14%E9%9B%86%5D%5B%E9%9F%A9%E8%AF%AD%E4%B8%AD%E5%AD%97%5D%5B720p%5D.mp4"
        },
        {
            "name": "[\u97e9\u8ff7\u5b57\u5e55\u7ec4www.hanmi520.com][\u547d\u8fd0\u4e0e\u6124\u6012][\u7b2c15-16\u96c6][\u97e9\u8bed\u4e2d\u5b57][720p].mp4",
            "action": "magnet:?xt=urn:btih:0d6fe5b9142b89f92b49036531466fd4840109f3&dn=%5B%E9%9F%A9%E8%BF%B7%E5%AD%97%E5%B9%95%E7%BB%84www.hanmi520.com%5D%5B%E5%91%BD%E8%BF%90%E4%B8%8E%E6%84%A4%E6%80%92%5D%5B%E7%AC%AC15-16%E9%9B%86%5D%5B%E9%9F%A9%E8%AF%AD%E4%B8%AD%E5%AD%97%5D%5B720p%5D.mp4"
        },
        {
            "name": "[\u97e9\u8ff7\u5b57\u5e55\u7ec4www.hanmi520.com][\u547d\u8fd0\u4e0e\u6124\u6012][\u7b2c19-20\u96c6][\u97e9\u8bed\u4e2d\u5b57][720p].mp4",
            "action": "magnet:?xt=urn:btih:0da5ad083ef2f5b5968f7a0c42975227ee92b4bc&dn=%5B%E9%9F%A9%E8%BF%B7%E5%AD%97%E5%B9%95%E7%BB%84www.hanmi520.com%5D%5B%E5%91%BD%E8%BF%90%E4%B8%8E%E6%84%A4%E6%80%92%5D%5B%E7%AC%AC19-20%E9%9B%86%5D%5B%E9%9F%A9%E8%AF%AD%E4%B8%AD%E5%AD%97%5D%5B720p%5D.mp4"
        },
        {
            "name": "[\u97e9\u8ff7\u5b57\u5e55\u7ec4www.hanmi520.com][\u547d\u8fd0\u4e0e\u6124\u6012][\u7b2c05-06\u96c6][\u97e9\u8bed\u4e2d\u5b57][720p].mp4",
            "action": "magnet:?xt=urn:btih:127673ca2a145e5ce6724122b30a747cc45f968c&dn=%5B%E9%9F%A9%E8%BF%B7%E5%AD%97%E5%B9%95%E7%BB%84www.hanmi520.com%5D%5B%E5%91%BD%E8%BF%90%E4%B8%8E%E6%84%A4%E6%80%92%5D%5B%E7%AC%AC05-06%E9%9B%86%5D%5B%E9%9F%A9%E8%AF%AD%E4%B8%AD%E5%AD%97%5D%5B720p%5D.mp4"
        },
        {
            "name": "[\u97e9\u8ff7\u5b57\u5e55\u7ec4www.hanmi520.com][\u547d\u8fd0\u4e0e\u6124\u6012][\u7b2c09-10\u96c6][\u97e9\u8bed\u4e2d\u5b57][720p].mp4",
            "action": "magnet:?xt=urn:btih:120bf054bbeafbad3909e9f103d6f9d4362ae6da&dn=%5B%E9%9F%A9%E8%BF%B7%E5%AD%97%E5%B9%95%E7%BB%84www.hanmi520.com%5D%5B%E5%91%BD%E8%BF%90%E4%B8%8E%E6%84%A4%E6%80%92%5D%5B%E7%AC%AC09-10%E9%9B%86%5D%5B%E9%9F%A9%E8%AF%AD%E4%B8%AD%E5%AD%97%5D%5B720p%5D.mp4"
        },
        {
            "name": "[\u97e9\u8ff7\u5b57\u5e55\u7ec4www.hanmi520.com][\u547d\u8fd0\u4e0e\u6124\u6012][\u7b2c25-26\u96c6][\u97e9\u8bed\u4e2d\u5b57][720p].mp4",
            "action": "magnet:?xt=urn:btih:12ce8de7ea0470259ba818bd14256071e8650c62&dn=%5B%E9%9F%A9%E8%BF%B7%E5%AD%97%E5%B9%95%E7%BB%84www.hanmi520.com%5D%5B%E5%91%BD%E8%BF%90%E4%B8%8E%E6%84%A4%E6%80%92%5D%5B%E7%AC%AC25-26%E9%9B%86%5D%5B%E9%9F%A9%E8%AF%AD%E4%B8%AD%E5%AD%97%5D%5B720p%5D.mp4"
        },
        {
            "name": "www.tskscn.com(\u547d\u8fd0\u4e0e\u6124\u6012)",
            "action": "magnet:?xt=urn:btih:176f5724dc549cd8546ced589f5ba5164c2452bb&dn=www.tskscn.com%28%E5%91%BD%E8%BF%90%E4%B8%8E%E6%84%A4%E6%80%92%29"
        },
        {
            "name": "www.tskscn.com(\u547d\u8fd0\u4e0e\u6124\u6012)",
            "action": "magnet:?xt=urn:btih:1e5017e927a224faf7f8381beeea93c1aa7d6b77&dn=www.tskscn.com%28%E5%91%BD%E8%BF%90%E4%B8%8E%E6%84%A4%E6%80%92%29"
        },
        {
            "name": "[\u97e9\u8ff7\u5b57\u5e55\u7ec4www.hanmi520.com][\u547d\u8fd0\u4e0e\u6124\u6012][\u7b2c17-18\u96c6][\u97e9\u8bed\u4e2d\u5b57][720p].mp4",
            "action": "magnet:?xt=urn:btih:311f972b6f8db5430312ab20e0b21d61b56a7d35&dn=%5B%E9%9F%A9%E8%BF%B7%E5%AD%97%E5%B9%95%E7%BB%84www.hanmi520.com%5D%5B%E5%91%BD%E8%BF%90%E4%B8%8E%E6%84%A4%E6%80%92%5D%5B%E7%AC%AC17-18%E9%9B%86%5D%5B%E9%9F%A9%E8%AF%AD%E4%B8%AD%E5%AD%97%5D%5B720p%5D.mp4"
        },
        {
            "name": "[\u97e9\u8ff7\u5b57\u5e55\u7ec4www.hanmi520.com][\u547d\u8fd0\u4e0e\u6124\u6012][\u7b2c01-02\u96c6][\u97e9\u8bed\u4e2d\u5b57][720p].mp4",
            "action": "magnet:?xt=urn:btih:33ad769bcfee0a4d17a4274559ba66d8cf358c9e&dn=%5B%E9%9F%A9%E8%BF%B7%E5%AD%97%E5%B9%95%E7%BB%84www.hanmi520.com%5D%5B%E5%91%BD%E8%BF%90%E4%B8%8E%E6%84%A4%E6%80%92%5D%5B%E7%AC%AC01-02%E9%9B%86%5D%5B%E9%9F%A9%E8%AF%AD%E4%B8%AD%E5%AD%97%5D%5B720p%5D.mp4"
        },
        {
            "name": "[\u97e9\u8ff7\u5b57\u5e55\u7ec4www.hanmi520.com][\u547d\u8fd0\u4e0e\u6124\u6012][\u7b2c39-40\u96c6\u5927\u7ed3\u5c40][\u97e9\u8bed\u4e2d\u5b57][720p].mp4",
            "action": "magnet:?xt=urn:btih:567d8574079da894e203ef81a26525e0d4676581&dn=%5B%E9%9F%A9%E8%BF%B7%E5%AD%97%E5%B9%95%E7%BB%84www.hanmi520.com%5D%5B%E5%91%BD%E8%BF%90%E4%B8%8E%E6%84%A4%E6%80%92%5D%5B%E7%AC%AC39-40%E9%9B%86%E5%A4%A7%E7%BB%93%E5%B1%80%5D%5B%E9%9F%A9%E8%AF%AD%E4%B8%AD%E5%AD%97%5D%5B720p%5D.mp4"
        },
        {
            "name": "[\u97e9\u8ff7\u5b57\u5e55\u7ec4www.hanmi520.com][\u547d\u8fd0\u4e0e\u6124\u6012][\u7b2c27-28\u96c6][\u97e9\u8bed\u4e2d\u5b57][720p].mp4",
            "action": "magnet:?xt=urn:btih:61dbef82bf78d653dcc1db5203bf6c6f80cbdf0b&dn=%5B%E9%9F%A9%E8%BF%B7%E5%AD%97%E5%B9%95%E7%BB%84www.hanmi520.com%5D%5B%E5%91%BD%E8%BF%90%E4%B8%8E%E6%84%A4%E6%80%92%5D%5B%E7%AC%AC27-28%E9%9B%86%5D%5B%E9%9F%A9%E8%AF%AD%E4%B8%AD%E5%AD%97%5D%5B720p%5D.mp4"
        },
        {
            "name": "[\u97e9\u8ff7\u5b57\u5e55\u7ec4www.hanmi520.com][\u547d\u8fd0\u4e0e\u6124\u6012][\u7b2c31-32\u96c6][\u97e9\u8bed\u4e2d\u5b57][720p].mp4",
            "action": "magnet:?xt=urn:btih:6972c7860b565d8d59039a273804d99be7b39d04&dn=%5B%E9%9F%A9%E8%BF%B7%E5%AD%97%E5%B9%95%E7%BB%84www.hanmi520.com%5D%5B%E5%91%BD%E8%BF%90%E4%B8%8E%E6%84%A4%E6%80%92%5D%5B%E7%AC%AC03-04%E9%9B%86%5D%5B%E9%9F%A9%E8%AF%AD%E4%B8%AD%E5%AD%97%5D%5B720p%5D.mp4"
        },
        {
            "name": "[\u97e9\u8ff7\u5b57\u5e55\u7ec4www.hanmi520.com][\u547d\u8fd0\u4e0e\u6124\u6012][\u7b2c03-04\u96c6][\u97e9\u8bed\u4e2d\u5b57][720p].mp4",
            "action": "magnet:?xt=urn:btih:949309e12cdd7823252959b138b4fc4302f60a3f&dn=%5B%E9%9F%A9%E8%BF%B7%E5%AD%97%E5%B9%95%E7%BB%84www.hanmi520.com%5D%5B%E5%91%BD%E8%BF%90%E4%B8%8E%E6%84%A4%E6%80%92%5D%5B%E7%AC%AC33-34%E9%9B%86%5D%5B%E9%9F%A9%E8%AF%AD%E4%B8%AD%E5%AD%97%5D%5B720p%5D.mp4"
        },
        {
            "name": "[\u97e9\u8ff7\u5b57\u5e55\u7ec4www.hanmi520.com][\u547d\u8fd0\u4e0e\u6124\u6012][\u7b2c37-38\u96c6][\u97e9\u8bed\u4e2d\u5b57][720p].mp4",
            "action": "magnet:?xt=urn:btih:96a634f6dd0c9d2bcf8410759aa8fe62e927137c&dn=%5B%E9%9F%A9%E8%BF%B7%E5%AD%97%E5%B9%95%E7%BB%84www.hanmi520.com%5D%5B%E5%91%BD%E8%BF%90%E4%B8%8E%E6%84%A4%E6%80%92%5D%5B%E7%AC%AC23-24%E9%9B%86%5D%5B%E9%9F%A9%E8%AF%AD%E4%B8%AD%E5%AD%97%5D%5B720p%5D.mp4"
        }
    ]
}