{
    "\u5510\u987f\u5e84\u56ed \u7b2c\u516d\u5b63": [
        {
            "name": "\u5510\u987f\u5e84\u56ed \u7b2c\u516d\u5b63.\u51688\u96c6.1080p-hdmee",
            "action": "magnet:?xt=urn:btih:8b4b772fbd0fa54dbfba9b752c57c689754a63d4&dn=%E5%94%90%E9%A1%BF%E5%BA%84%E5%9B%AD%20%E7%AC%AC%E5%85%AD%E5%AD%A3.%E5%85%A88%E9%9B%86.1080P-HdMee"
        },
        {
            "name": "\u5510\u987f\u5e84\u56ed \u7b2c\u516d\u5b63\u5b63\u7ec8 .\u66f4\u591a\u514d\u8d39\u8d44\u6e90\u5173\u6ce8\u5fae\u4fe1\u516c\u4f17\u53f7 \uff1alydysc2017",
            "action": "magnet:?xt=urn:btih:8f1d4aef94ba618aa190fefcdb8fac5c0213353b&dn=%E5%94%90%E9%A1%BF%E5%BA%84%E5%9B%AD%20%E7%AC%AC%E5%85%AD%E5%AD%A3%E5%AD%A3%E7%BB%88%20.%E6%9B%B4%E5%A4%9A%E5%85%8D%E8%B4%B9%E8%B5%84%E6%BA%90%E5%85%B3%E6%B3%A8%E5%BE%AE%E4%BF%A1%E5%85%AC%E4%BC%97%E5%8F%B7%20%EF%BC%9Alydysc2017"
        },
        {
            "name": "\u5510\u987f\u5e84\u56ed \u7b2c\u516d\u5b63 .\u66f4\u591a\u514d\u8d39\u8d44\u6e90\u5173\u6ce8\u5fae\u4fe1\u516c\u4f17\u53f7 \uff1alydysc2017",
            "action": "magnet:?xt=urn:btih:ff47e622d1de490f43a38fe3691de069e76fd183&dn=%E5%94%90%E9%A1%BF%E5%BA%84%E5%9B%AD%20%E7%AC%AC%E5%85%AD%E5%AD%A3%20.%E6%9B%B4%E5%A4%9A%E5%85%8D%E8%B4%B9%E8%B5%84%E6%BA%90%E5%85%B3%E6%B3%A8%E5%BE%AE%E4%BF%A1%E5%85%AC%E4%BC%97%E5%8F%B7%20%EF%BC%9Alydysc2017"
        }
    ]
}