{
    "\u666e\u901a\u7684\u604b\u7231": [
        {
            "name": "[yyets.com][\u666e\u901a \u604b\u7231][e03.120307][\u97e9\u8bed\u4e2d\u5b57][hr-hdtv][yyets_\u97e9\u5267\u7cbe\u7075].mkv",
            "action": "magnet:?xt=urn:btih:02f20ff90aaebf6eea7b8271facc38e309c79b46&dn=%5BYYeTs.com%5D%5B%E6%99%AE%E9%80%9A%E7%9A%84%E6%81%8B%E7%88%B1%5D%5BE03.120307%5D%5B%E9%9F%A9%E8%AF%AD%E4%B8%AD%E5%AD%97%5D%5BHR-HDTV%5D%5BYYeTs_%E9%9F%A9%E5%89%A7%E7%B2%BE%E7%81%B5%5D.mkv"
        },
        {
            "name": "[yyets.com][\u666e\u901a \u604b\u7231][e04.end.120308][\u97e9\u8bed\u4e2d\u5b57][hr-hdtv][yyets_\u97e9\u5267\u7cbe\u7075].mkv",
            "action": "magnet:?xt=urn:btih:17042e08904d0b89bb333269e6590c4079f57062&dn=%5BYYeTs.com%5D%5B%E6%99%AE%E9%80%9A%E7%9A%84%E6%81%8B%E7%88%B1%5D%5BE04.End.120308%5D%5B%E9%9F%A9%E8%AF%AD%E4%B8%AD%E5%AD%97%5D%5BHR-HDTV%5D%5BYYeTs_%E9%9F%A9%E5%89%A7%E7%B2%BE%E7%81%B5%5D.mkv"
        },
        {
            "name": "[yyets.com][\u666e\u901a \u604b\u7231][e01.120229][\u97e9\u8bed\u4e2d\u5b57][hr-hdtv][yyets_\u97e9\u5267\u7cbe\u7075].mkv",
            "action": "magnet:?xt=urn:btih:4c61259d54214d01b768dbeaf9ae20eda94183a4&dn=%5BYYeTs.com%5D%5B%E6%99%AE%E9%80%9A%E7%9A%84%E6%81%8B%E7%88%B1%5D%5BE01.120229%5D%5B%E9%9F%A9%E8%AF%AD%E4%B8%AD%E5%AD%97%5D%5BHR-HDTV%5D%5BYYeTs_%E9%9F%A9%E5%89%A7%E7%B2%BE%E7%81%B5%5D.mkv"
        },
        {
            "name": "[\u666e\u901a \u604b\u7231][e01.120229][\u97e9\u8bed\u4e2d\u5b57][hdtv-rmvb][\u97e9\u5267\u7cbe\u7075].rmvb",
            "action": "magnet:?xt=urn:btih:5efffa28c6c206dfd099d2689e6bea64984a56ef&dn=%5B%E6%99%AE%E9%80%9A%E7%9A%84%E6%81%8B%E7%88%B1%5D%5BE01.120229%5D%5B%E9%9F%A9%E8%AF%AD%E4%B8%AD%E5%AD%97%5D%5BHDTV-RMVB%5D%5B%E9%9F%A9%E5%89%A7%E7%B2%BE%E7%81%B5%5D.rmvb"
        },
        {
            "name": "[\u666e\u901a \u604b\u7231][e04.end.120308][\u97e9\u8bed\u4e2d\u5b57][hdtv-rmvb][\u97e9\u5267\u7cbe\u7075].rmvb",
            "action": "magnet:?xt=urn:btih:87b2bcf41f58232e7bdd2e3c3ebc2e3eb9ef9462&dn=%5B%E6%99%AE%E9%80%9A%E7%9A%84%E6%81%8B%E7%88%B1%5D%5BE04.End.120308%5D%5B%E9%9F%A9%E8%AF%AD%E4%B8%AD%E5%AD%97%5D%5BHDTV-RMVB%5D%5B%E9%9F%A9%E5%89%A7%E7%B2%BE%E7%81%B5%5D.rmvb"
        },
        {
            "name": "[yyets.com][\u666e\u901a \u604b\u7231][e02.120301][\u97e9\u8bed\u4e2d\u5b57][hr-hdtv][yyets_\u97e9\u5267\u7cbe\u7075].mkv",
            "action": "magnet:?xt=urn:btih:c3ea5aae1b3861be3f6adfb7a38a06bb55680a1e&dn=%5BYYeTs.com%5D%5B%E6%99%AE%E9%80%9A%E7%9A%84%E6%81%8B%E7%88%B1%5D%5BE02.120301%5D%5B%E9%9F%A9%E8%AF%AD%E4%B8%AD%E5%AD%97%5D%5BHR-HDTV%5D%5BYYeTs_%E9%9F%A9%E5%89%A7%E7%B2%BE%E7%81%B5%5D.mkv"
        },
        {
            "name": "[\u666e\u901a \u604b\u7231][e03.120307][\u97e9\u8bed\u4e2d\u5b57][hdtv-rmvb][\u97e9\u5267\u7cbe\u7075].rmvb",
            "action": "magnet:?xt=urn:btih:c4b090ff351179f915296c5db4c738e40598419f&dn=%5B%E6%99%AE%E9%80%9A%E7%9A%84%E6%81%8B%E7%88%B1%5D%5BE03.120307%5D%5B%E9%9F%A9%E8%AF%AD%E4%B8%AD%E5%AD%97%5D%5BHDTV-RMVB%5D%5B%E9%9F%A9%E5%89%A7%E7%B2%BE%E7%81%B5%5D.rmvb"
        },
        {
            "name": "[\u666e\u901a \u604b\u7231][e02.120301][\u97e9\u8bed\u4e2d\u5b57][hdtv-rmvb][\u97e9\u5267\u7cbe\u7075].rmvb",
            "action": "magnet:?xt=urn:btih:f9018a71a6aa3b7e225624f2d6c76fa8d0e86523&dn=%5B%E6%99%AE%E9%80%9A%E7%9A%84%E6%81%8B%E7%88%B1%5D%5BE02.120301%5D%5B%E9%9F%A9%E8%AF%AD%E4%B8%AD%E5%AD%97%5D%5BHDTV-RMVB%5D%5B%E9%9F%A9%E5%89%A7%E7%B2%BE%E7%81%B5%5D.rmvb"
        }
    ]
}