{
    "\u730e\u573a": [
        {
            "name": "\u730e\u573a\u3002\u5fae\u4fe1\u516c\u4f17\u53f7\uff1aaydays",
            "action": "magnet:?xt=urn:btih:33f0ea64352106f2762564a250b3409e172f01c7&dn=%E7%8C%8E%E5%9C%BA%E3%80%82%E5%BE%AE%E4%BF%A1%E5%85%AC%E4%BC%97%E5%8F%B7%EF%BC%9Aaydays"
        },
        {
            "name": "\u730e\u573a",
            "action": "magnet:?xt=urn:btih:0077ee2faf0f615ac2c816f83daabb766ec85cc4&dn=%E7%8C%8E%E5%9C%BA"
        },
        {
            "name": "\u730e.\u573a51-58\u96c6",
            "action": "magnet:?xt=urn:btih:00515a3df587f14f9efaf776d737393d5fe68936&dn=%E7%8C%8E.%E5%9C%BA51-58%E9%9B%86"
        },
        {
            "name": "\u730e\u573a1-2\u96c6\uff08\u5fae\u4fe1\u516c\u4f17\u53f7v  n2016\uff09",
            "action": "magnet:?xt=urn:btih:02ce46b029b41f6358accbcb16a61146ed66c6ad&dn=%5BWEBHD%5D%E7%8C%8E%E5%9C%BA%20Game.of.Hunting.2017.E30.WEB-DL.1080p.H264.AAC-WEBHD"
        },
        {
            "name": "[webhd]\u730e\u573a     .of.   ting.2017.e30.web-dl.1080p.h2  .aac-webhd",
            "action": "magnet:?xt=urn:btih:044ac050d619ec03a475ea440d8381ec2bcb0d16&dn=%E7%8C%8E%E5%9C%BA%2039-40"
        },
        {
            "name": "\u730e\u573a",
            "action": "magnet:?xt=urn:btih:0b410d88f18fcbd0ddae812576c6899011df0cec&dn=%E7%8C%8E%E5%9C%BA25-26"
        },
        {
            "name": "\u730e\u573a 39-40",
            "action": "magnet:?xt=urn:btih:1aba0b082921f5870f2e70fcea687d136ad53fb4&dn=%E7%8C%8E%E5%9C%BA%E3%80%82%E5%BE%AE%E4%BF%A1%E5%85%AC%E4%BC%97%E5%8F%B7%EF%BC%9Aaydays"
        },
        {
            "name": "\u730e\u573a25-26",
            "action": "magnet:?xt=urn:btih:1bd4aed37b32dfbf7675b3b82facaa36fcd17c95&dn=%E7%8C%8E%E5%9C%BA%E3%80%82%E5%BE%AE%E4%BF%A1%E5%85%AC%E4%BC%97%E5%8F%B7%EF%BC%9ABT9555"
        },
        {
            "name": "\u730e\u573a\u3002\u5fae\u4fe1\u516c\u4f17\u53f7\uff1aaydays",
            "action": "magnet:?xt=urn:btih:1b3cf184e4dcabb21ffefa680a364c679be8d370&dn=%5BWEBHD%5D%E7%8C%8E%E5%9C%BA%20Game.of.Hunting.2017.E40.WEB-DL.1080p.H264.AAC-WEBHD"
        },
        {
            "name": "\u730e\u573a\u3002\u5fae\u4fe1\u516c\u4f17\u53f7\uff1a  9555",
            "action": "magnet:?xt=urn:btih:1ed9c6a2875ad674a90ca5b128e9bc34dd51a2bb&dn=%5B%E5%B0%8F%E5%8D%AB%E5%BD%B1%E8%A7%86%5D%5B%E5%AE%98%E6%96%B9QQ%E7%BE%A4%EF%BC%9A206637316%5D%5B%E7%8C%8E%E5%9C%BA%5D%5B2017%5D%5B23-24%5D%5B%E5%9B%BD%E8%AF%AD%E4%B8%AD%E5%AD%97%5D%5BMP4%5D%5B720P%5D%5B%E5%8D%AB%E8%A7%86%E7%89%88%E6%9C%AC%5D"
        },
        {
            "name": "[webhd]\u730e\u573a     .of.   ting.2017.e40.web-dl.1080p.h2  .aac-webhd",
            "action": "magnet:?xt=urn:btih:1e771a4b08d9f06b43c01dc91539be28df504cdf&dn=%5BWEBHD%5D%E7%8C%8E%E5%9C%BA%20Game.of.Hunting.2017.E42-E43.WEB-DL.1080p.H264.AAC-WEBHD"
        },
        {
            "name": "[\u5c0f\u536b\u5f71\u89c6][  qq\u7fa4\uff1a206637316][\u730e\u573a][2017][23-24][\u56fd\u8bed\u4e2d\u5b57][mp4][720p][\u536b\u89c6\u7248 ]",
            "action": "magnet:?xt=urn:btih:22acaf50effcb436f80ece0928a403571a20bfa4&dn=%5BWEBHD%5D%E7%8C%8E%E5%9C%BA%20Game.of.Hunting.2017.E31.WEB-DL.1080p.H264.AAC-WEBHD"
        },
        {
            "name": "[webhd]\u730e\u573a     .of.   ting.2017.e42-e43.web-dl.1080p.h2  .aac-webhd",
            "action": "magnet:?xt=urn:btih:23b620037280352fb1df9d27469a64b83178ce1f&dn=%E7%8C%8E%E5%9C%BA%E3%80%82%E5%BE%AE%E4%BF%A1%E5%85%AC%E4%BC%97%E5%8F%B7%EF%BC%9Aaydays"
        },
        {
            "name": "[webhd]\u730e\u573a     .of.   ting.2017.e31.web-dl.1080p.h2  .aac-webhd",
            "action": "magnet:?xt=urn:btih:247aea35589d048a38e483720c41371df87b4863&dn=%5BWEBHD%5D%E7%8C%8E%E5%9C%BA%20Game.of.Hunting.2017.Complete.WEB-DL.1080p.H264.AAC-WEBHD"
        },
        {
            "name": "\u730e\u573a\u3002\u5fae\u4fe1\u516c\u4f17\u53f7\uff1aaydays",
            "action": "magnet:?xt=urn:btih:283623146f182f365b496fad23fe12476f7970b6&dn=%5BWEBHD%5D%E7%8C%8E%E5%9C%BA%20Game.of.Hunting.2017.Complete.WEB-DL.1080p.H264.AAC-WEBHD"
        },
        {
            "name": "[webhd]\u730e\u573a     .of.   ting.2017.complete.web-dl.1080p.h2  .aac-webhd",
            "action": "magnet:?xt=urn:btih:2bc810ecd7d0b8c53711fae8a9b1488ac04d98bc&dn=%5BWEBHD%5D%E7%8C%8E%E5%9C%BA%20Game.of.Hunting.2017.E37.WEB-DL.1080p.H264.AAC-WEBHD"
        },
        {
            "name": "[webhd]\u730e\u573a     .of.   ting.2017.complete.web-dl.1080p.h2  .aac-webhd",
            "action": "magnet:?xt=urn:btih:2cb67b6da2d72273e1d3bb2db30106f6fc36d0d6&dn=%E7%8C%8E%E5%9C%BA1-4%E9%9B%86"
        },
        {
            "name": "[webhd]\u730e\u573a     .of.   ting.2017.e37.web-dl.1080p.h2  .aac-webhd",
            "action": "magnet:?xt=urn:btih:2cee5a982401e645f6e05f930835126bffacbcd9&dn=%5BWEBHD%5D%E7%8C%8E%E5%9C%BA%20Game.of.Hunting.2017.E16-E17.WEB-DL.1080p.H264.AAC-WEBHD"
        }
    ]
}