{
    "\u732b\u4e0e\u6843\u82b1\u6e90": [
        {
            "name": "\u732b\u4e0e\u6843\u82b1\u6e90.cats.and.peachtopia.2018.4k.1080p.web-dl.x2  .aac.manda  n.chs.eng-dygc",
            "action": "magnet:?xt=urn:btih:16b42d7caf87a205afcd1c1b843530f809db39f5&dn=%E7%8C%AB%E4%B8%8E%E6%A1%83%E8%8A%B1%E6%BA%90.Cats.and.Peachtopia.2018.4K.1080P.WEB-DL.X264.AAC.Mandarin.CHS.ENG-DYGC"
        },
        {
            "name": "\u732b\u4e0e\u6843\u82b1\u6e90.cats.and.peachtopia.2018.1080p.web-dl.x2  .aac-\u56fd\u8bed\u4e2d\u5b57-mp4ba",
            "action": "magnet:?xt=urn:btih:5bf557d35294ad9df78db6fb5c90ac5a1b86d500&dn=%E7%8C%AB%E4%B8%8E%E6%A1%83%E8%8A%B1%E6%BA%90.Cats.and.Peachtopia.2018.HD1080P.x264.%E5%9B%BD%E8%AF%AD%E4%B8%AD%E5%AD%97.Mandarin.chs.btrenren.mp4"
        },
        {
            "name": "\u732b\u4e0e\u6843\u82b1\u6e90.cats.and.peachtopia.2018.hd1080p.x2  .\u56fd\u8bed\u4e2d\u5b57.manda  n.chs.  renren.mp4",
            "action": "magnet:?xt=urn:btih:61655d7a781c4f663977eda1dfb0ca474742fbd3&dn=%E7%8C%AB%E4%B8%8E%E6%A1%83%E8%8A%B1%E6%BA%90.Cats.and.Peachtopia.2018.1080p.WEB-DL.X264.AAC-%E5%9B%BD%E8%AF%AD%E4%B8%AD%E5%AD%97-RARBT"
        },
        {
            "name": "\u732b\u4e0e\u6843\u82b1\u6e90.cats.and.peachtopia.2018.1080p.web-dl.x2  .aac-\u56fd\u8bed\u4e2d\u5b57-rar  ",
            "action": "magnet:?xt=urn:btih:7ab53c07d800b71d372a7ea4ba93e8f2279ec7f3&dn=%5B%E7%8C%AB%E4%B8%8E%E6%A1%83%E8%8A%B1%E6%BA%90%20%5D%E5%9B%BD%E8%AF%AD%E4%B8%AD%E5%AD%97.Cats.and.Peachtopia.2018.1080p.WEB-DL.MP4.x264.AAC-CnSCG"
        },
        {
            "name": "[\u732b\u4e0e\u6843\u82b1\u6e90 ]\u56fd\u8bed\u4e2d\u5b57.cats.and.peachtopia.2018.1080p.web-dl.mp4.x2  .aac-cnscg",
            "action": "magnet:?xt=urn:btih:94132be5b0e8ca2b75fc64b0285b7e84f38e429f&dn=%E7%8C%AB%E4%B8%8E%E6%A1%83%E8%8A%B1%E6%BA%90-%E5%9B%BD%E8%AF%AD1080P.2018.WEB-DL.X264.AAC-SEEHD"
        },
        {
            "name": "\u732b\u4e0e\u6843\u82b1\u6e90-\u56fd\u8bed1080p.2018.web-dl.x2  .aac-seehd",
            "action": "magnet:?xt=urn:btih:a69092189a5a9db3aa4321d9dbaf9824cd93d084&dn=%E7%8C%AB%E4%B8%8E%E6%A1%83%E8%8A%B1%E6%BA%90.Cats.and.Peachtopia.2018.1080p.WEB-DL.X264.AAC-BTBT4K"
        },
        {
            "name": "\u732b\u4e0e\u6843\u82b1\u6e90.cats.and.peachtopia.2018.1080p.web-dl.x2  .aac-    4k",
            "action": "magnet:?xt=urn:btih:df149a26de7f4bb58b2ee2ea1eefa3f7ca2ca5f2&dn=%5BViPHD%5D%E7%8C%AB%E4%B8%8E%E6%A1%83%E8%8A%B1%E6%BA%90%20Cats.and.Peachtopia.2018.WEB-DL.1080P%262160P.H264.AAC-JBY%40ViPHD"
        },
        {
            "name": "[viphd]\u732b\u4e0e\u6843\u82b1\u6e90 cats.and.peachtopia.2018.web-dl.1080p&2160p.h2  .aac-  y@viphd",
            "action": "magnet:?xt=urn:btih:185e83bfa7aff9c34184155ea92a3fb05462f1e7&dn=%E7%8C%AB%E4%B8%8E%E6%A1%83%E8%8A%B1%E6%BA%90BD%E5%9B%BD%E8%AF%AD%E4%B8%AD%E5%AD%97.mp4"
        },
        {
            "name": "\u732b\u4e0e\u6843\u82b1\u6e90bd\u56fd\u8bed\u4e2d\u5b57.mp4",
            "action": "magnet:?xt=urn:btih:2e4822f79a692d168b2aac597434e41cbea5f829&dn=%E7%8C%AB%E4%B8%8E%E6%A1%83%E8%8A%B1%E6%BA%90.Cats.and.Peachtopia.2018.WEB-1080p.X264.AAC-99Mp4.mp4"
        },
        {
            "name": "\u732b\u4e0e\u6843\u82b1\u6e90.cats.and.peachtopia.2018.web-1080p.x2  .aac-99mp4.mp4",
            "action": "magnet:?xt=urn:btih:5a4a3667a643135ac7aeac8510004171673b9f1a&dn=%5B%E7%94%B5%E5%BD%B1%E5%A4%A9%E5%A0%82www.dy2018.com%5D%E7%8C%AB%E4%B8%8E%E6%A1%83%E8%8A%B1%E6%BA%90HD%E9%AB%98%E6%B8%85%E5%9B%BD%E8%AF%AD%E4%B8%AD%E5%AD%97.mp4"
        },
        {
            "name": "[  \u5929\u5802www.dy2018.com]\u732b\u4e0e\u6843\u82b1\u6e90hd\u9ad8\u6e05\u56fd\u8bed\u4e2d\u5b57.mp4",
            "action": "magnet:?xt=urn:btih:8460704e40a88b1c5d07677dba82be91a1e41834&dn=%E7%8C%AB%E4%B8%8E%E6%A1%83%E8%8A%B1%E6%BA%90.mp4"
        },
        {
            "name": "\u732b\u4e0e\u6843\u82b1\u6e90.mp4",
            "action": "magnet:?xt=urn:btih:aae035a580e03ba40bd29571a7f9eaf6e6e27e17&dn=%E9%98%B3%E5%85%89%E7%94%B5%E5%BD%B1www.ygdy8.com.%E7%8C%AB%E4%B8%8E%E6%A1%83%E8%8A%B1%E6%BA%90.HD.720p.%E5%9B%BD%E8%AF%AD%E4%B8%AD%E8%8B%B1%E5%8F%8C%E5%AD%97.mkv"
        },
        {
            "name": "\u9633\u5149  www.ygdy8.com.\u732b\u4e0e\u6843\u82b1\u6e90.hd.720p.\u56fd\u8bed\u4e2d\u82f1\u53cc\u5b57.mkv",
            "action": "magnet:?xt=urn:btih:be24174a856ac8cb067967da4e0ec55655b451d8&dn=%E7%8C%AB%E4%B8%8E%E6%A1%83%E8%8A%B1%E6%BA%90.Cats.and.Peachtopia.2018.HD720P.X264.AAC.Mandarin.CHS.mp4"
        },
        {
            "name": "\u732b\u4e0e\u6843\u82b1\u6e90.cats.and.peachtopia.2018.hd720p.x2  .aac.manda  n.chs.mp4",
            "action": "magnet:?xt=urn:btih:ca9bddbe87d0bd1171e8b3d4edef41a871396fb4&dn=%E7%8C%AB%E4%B8%8E%E6%A1%83%E8%8A%B1%E6%BA%90HD1080P%E9%AB%98%E6%B8%85%E5%9B%BD%E8%AF%AD%E4%B8%AD%E5%AD%97.mp4"
        },
        {
            "name": "\u732b\u4e0e\u6843\u82b1\u6e90hd1080p\u9ad8\u6e05\u56fd\u8bed\u4e2d\u5b57.mp4",
            "action": "magnet:?xt=urn:btih:f72be745ed98ae1fdf67a6119421bc38c62bd9cc&dn=%5B135bt%E7%BD%91%5D%5B135bt.net%5D%5BHD%5D%5B1.3GB%5D%E7%8C%AB%E4%B8%8E%E6%A1%83%E8%8A%B1%E6%BA%90.%E5%9B%BD%E8%AF%AD%E4%B8%AD%E5%AD%97.mp4"
        },
        {
            "name": "\u732b\u4e0e\u6843\u82b1\u6e90.2018.bd1280\u9ad8\u6e05\u4e2d\u82f1\u53cc\u5b57-www.iidvd.com.mp4",
            "action": "magnet:?xt=urn:btih:2633bb1a37da737a3365e605c8a67db4536b3154&dn=Cats.and.Peachtopia.2018.1080p.WEB-DL.x264"
        }
    ]
}