{
    "\u8d34\u8eab\u5973\u4fdd\u9556": [
        {
            "name": "[\u6709\u9ad8\u6e05  \u7f51][yougaoqing.com][\u8d34\u8eab\u5973\u4fdd\u9556]close.2019.1080p.nf.web  p.ddp5.1.x2  -  ",
            "action": "magnet:?xt=urn:btih:106bfbb4bc64cd7f5d612d0f28217fd9d7a1f140&dn=%5B%E6%9C%89%E9%AB%98%E6%B8%85%E7%94%B5%E5%BD%B1%E7%BD%91%5D%5Byougaoqing.com%5D%5B%E8%B4%B4%E8%BA%AB%E5%A5%B3%E4%BF%9D%E9%95%96%5DClose.2019.1080p.NF.WEBRip.DDP5.1.x264-CM"
        },
        {
            "name": "\u8d34\u8eab\u5973\u4fdd\u9556.close.2019.1080p.web  p.x2  .chs.eng-lieqiwang",
            "action": "magnet:?xt=urn:btih:1249d09f93ea34c093b583bb86479c3094960ba5&dn=%E8%B4%B4%E8%BA%AB%E5%A5%B3%E4%BF%9D%E9%95%96.Close.2019.1080p.WEBRip.x264.CHS.ENG-Lieqiwang"
        },
        {
            "name": "\u8d34\u8eab\u5973\u4fdd\u9556.close.2019.hd1080p.aac.x2  .english.chs.  dx8",
            "action": "magnet:?xt=urn:btih:17cc177d16d11604b7b10e40611627593cee6356&dn=%E8%B4%B4%E8%BA%AB%E5%A5%B3%E4%BF%9D%E9%95%96.Close.2019.HD1080P.AAC.x264.English.CHS.BTDX8"
        },
        {
            "name": "\u8d34\u8eab\u5973\u4fdd\u9556.close.2019.1080p.web  p.x2  -\u4e2d\u82f1\u53cc\u5b57-rar  ",
            "action": "magnet:?xt=urn:btih:1ad1ec5163627f93c073a670f19cc628d0d54db1&dn=%E8%B4%B4%E8%BA%AB%E5%A5%B3%E4%BF%9D%E9%95%96.Close.2019.1080p.WEBRip.x264-%E4%B8%AD%E8%8B%B1%E5%8F%8C%E5%AD%97-RARBT"
        },
        {
            "name": "\u8d34\u8eab\u5973\u4fdd\u9556.close.2019.bd1080p.\u82f1\u8bed\u4e2d\u5b57.  dx8",
            "action": "magnet:?xt=urn:btih:1a449e7fca6fe593aeec50b0643b425123b0288a&dn=%E8%B4%B4%E8%BA%AB%E5%A5%B3%E4%BF%9D%E9%95%96.Close.2019.BD1080P.%E8%8B%B1%E8%AF%AD%E4%B8%AD%E5%AD%97.BTDX8"
        },
        {
            "name": "[2019.04.19]\u8d34\u8eab\u5973\u4fdd\u9556[2019\u5e74  \u52a8\u4f5c\u72af\u7f6a(mkv)]\uff08\u5e1d\u56fd\u51fa\u54c1\uff09",
            "action": "magnet:?xt=urn:btih:1ca3ecefbc90296009fd7d952c4aaaa43f4f2368&dn=%5B2019.04.19%5D%E8%B4%B4%E8%BA%AB%E5%A5%B3%E4%BF%9D%E9%95%96%5B2019%E5%B9%B4%E7%BE%8E%E5%9B%BD%E5%8A%A8%E4%BD%9C%E7%8A%AF%E7%BD%AA%28MKV%29%5D%EF%BC%88%E5%B8%9D%E5%9B%BD%E5%87%BA%E5%93%81%EF%BC%89"
        },
        {
            "name": "\u8d34\u8eab\u5973\u4fdd\u9556.close.2019.1080p.web  p.x2  .chs.eng-    4k",
            "action": "magnet:?xt=urn:btih:27e3bbbcd43e854add19c1642e5c69968376b523&dn=%E8%B4%B4%E8%BA%AB%E5%A5%B3%E4%BF%9D%E9%95%96.Close.2019.1080p.WEBRip.x264.CHS.ENG-BTBT4K"
        },
        {
            "name": "\u8d34\u8eab\u5973\u4fdd\u95562019",
            "action": "magnet:?xt=urn:btih:42a32ae6f9412b11278f65819051f3cf7c1e05c4&dn=%E8%B4%B4%E8%BA%AB%E5%A5%B3%E4%BF%9D%E9%95%962019"
        },
        {
            "name": "\u8d34\u8eab\u5973\u4fdd\u9556.hd.1080p.mp4.2018.  .\u52a8\u4f5c.\u60ca\u609a.\u4e2d\u6587\u5b57\u5e55",
            "action": "magnet:?xt=urn:btih:537dd7a1904d1aefa7e9e53085540057d972f536&dn=%E8%B4%B4%E8%BA%AB%E5%A5%B3%E4%BF%9D%E9%95%96.HD.1080P.MP4.2018.%E7%BE%8E%E5%9B%BD.%E5%8A%A8%E4%BD%9C.%E6%83%8A%E6%82%9A.%E4%B8%AD%E6%96%87%E5%AD%97%E5%B9%95"
        },
        {
            "name": "\u8d34\u8eab\u5973\u4fdd\u9556.close.2019.hd720p.x2  .aac.english.chs-eng.mp4ba",
            "action": "magnet:?xt=urn:btih:588dd8134c896a0638c8471176a0bff04f67ac64&dn=%E8%B4%B4%E8%BA%AB%E5%A5%B3%E4%BF%9D%E9%95%96.Close.2019.HD720P.X264.AAC.English.CHS-ENG.Mp4Ba"
        },
        {
            "name": "\u8d34\u8eab\u5973\u4fdd\u9556.close.2019.hd1080p.x2  .aac.english.chs-eng.mp4ba",
            "action": "magnet:?xt=urn:btih:6a5ea77708ed5a19f6dc9706cb0dc79c745bc0e7&dn=%E8%B4%B4%E8%BA%AB%E5%A5%B3%E4%BF%9D%E9%95%96.Close.2019.HD1080P.X264.AAC.English.CHS-ENG.Mp4Ba"
        },
        {
            "name": "\u8d34\u8eab\u5973\u4fdd\u9556 close 2019.hd1080p.x2  .\u82f1\u8bed  \u4e2d\u6587\u5b57\u5e55.eng.chs.dd.5.1.kankan.ws",
            "action": "magnet:?xt=urn:btih:c6177316e70a4abf66a7cb089f9c4ee0dc9af696&dn=%E8%B4%B4%E8%BA%AB%E5%A5%B3%E4%BF%9D%E9%95%96%20Close%202019.HD1080P.x264.%E8%8B%B1%E8%AF%AD%E5%AE%98%E6%96%B9%E4%B8%AD%E6%96%87%E5%AD%97%E5%B9%95.Eng.Chs.DD.5.1.kankan.ws"
        },
        {
            "name": "\u8d34\u8eab\u5973\u4fdd\u9556.close.2019.bd720p.\u82f1\u8bed\u4e2d\u5b57.  dx8",
            "action": "magnet:?xt=urn:btih:ca3bf6aad2b7cefbba5e72da98c13ab3a93fd062&dn=%E8%B4%B4%E8%BA%AB%E5%A5%B3%E4%BF%9D%E9%95%96.Close.2019.BD720P.%E8%8B%B1%E8%AF%AD%E4%B8%AD%E5%AD%97.BTDX8"
        },
        {
            "name": "\u8d34\u8eab\u5973\u4fdd\u9556.close.2019.hd720p.aac.x2  .english.chs.  dx8",
            "action": "magnet:?xt=urn:btih:de4ac2dde438715c81f4cbe32f3780a2850fd549&dn=%E8%B4%B4%E8%BA%AB%E5%A5%B3%E4%BF%9D%E9%95%96.Close.2019.HD720P.AAC.x264.English.CHS.BTDX8"
        },
        {
            "name": "\u8d34\u8eab\u5973\u4fdd\u9556 close.2019.1080p.bl  ay.remux.  c.dts-hd.ma.5.1-homefei",
            "action": "magnet:?xt=urn:btih:e75019530f0de264d6da0642d4abed3ddba0fcba&dn=%E8%B4%B4%E8%BA%AB%E5%A5%B3%E4%BF%9D%E9%95%96%20Close.2019.1080p.BluRay.REMUX.AVC.DTS-HD.MA.5.1-homefei"
        },
        {
            "name": "\u8d34\u8eab\u5973\u4fdd\u9556.close.2019.1080p.web  p.x2  -\u4e2d\u82f1\u53cc\u5b57-mp4ba",
            "action": "magnet:?xt=urn:btih:fc54d9274593009683f2644a9f5a2b08efc31f81&dn=%E8%B4%B4%E8%BA%AB%E5%A5%B3%E4%BF%9D%E9%95%96.Close.2019.1080p.WEBRip.x264-%E4%B8%AD%E8%8B%B1%E5%8F%8C%E5%AD%97-MP4BA"
        },
        {
            "name": "\u8d34\u8eab\u5973\u4fdd\u9556.close.2019.\u4e2d\u82f1\u5b57\u5e55.web  p.aac.720p.x2  -lee.mp4",
            "action": "magnet:?xt=urn:btih:1a65e7800285bb63f601127c16532407774b1672&dn=%E8%B4%B4%E8%BA%AB%E5%A5%B3%E4%BF%9D%E9%95%96.Close.2019.%E4%B8%AD%E8%8B%B1%E5%AD%97%E5%B9%95.WEBrip.AAC.720P.x264-Lee.mp4"
        },
        {
            "name": "\u8d34\u8eab\u5973\u4fdd\u9556.close.2019.hd720p.x2  .aac.english.chs.mp4",
            "action": "magnet:?xt=urn:btih:394f6c49322cc308d177a84d1c08281d23e53103&dn=%E8%B4%B4%E8%BA%AB%E5%A5%B3%E4%BF%9D%E9%95%96.Close.2019.HD720P.X264.AAC.English.CHS.mp4"
        },
        {
            "name": "\u8d34\u8eab\u5973\u4fdd\u9556-\u56fd\u8bed720p.mp4",
            "action": "magnet:?xt=urn:btih:4c1b816018c2bbb4a86ea7c5fbe31b02a23dc94d&dn=%E8%B4%B4%E8%BA%AB%E5%A5%B3%E4%BF%9D%E9%95%96-%E5%9B%BD%E8%AF%AD720P.mp4"
        },
        {
            "name": "\u8d34\u8eab\u5973\u4fdd\u9556bd\u56fd\u8bed\u4e2d\u5b57.mp4",
            "action": "magnet:?xt=urn:btih:5b6c992c2c788351484b57701cea5b3316ada578&dn=%E8%B4%B4%E8%BA%AB%E5%A5%B3%E4%BF%9D%E9%95%96BD%E5%9B%BD%E8%AF%AD%E4%B8%AD%E5%AD%97.mp4"
        }
    ]
}