{
    "\u90a3\u5e741987": [
        {
            "name": "\u90a3\u5e741987.the.year.1987.2018.\u56fd\u8bed\u4e2d\u5b57.1080p.web-dl.x2  .aac-\u5723\u57ce\u5bb6\u56ed",
            "action": "magnet:?xt=urn:btih:13505621b8de3ddb687e42dc42b4ae43d5d1ef7e&dn=%E9%82%A3%E5%B9%B41987.The.Year.1987.2018.%E5%9B%BD%E8%AF%AD%E4%B8%AD%E5%AD%97.1080p.WEB-DL.x264.AAC-%E5%9C%A3%E5%9F%8E%E5%AE%B6%E5%9B%AD"
        },
        {
            "name": "\u90a3\u5e741987.2018.hd1080p.x2  .aac.manda  n.chs-eng.mp4ba",
            "action": "magnet:?xt=urn:btih:28bbfc2cd741c81cb8a2ba2c7588b2aaf995a216&dn=%E9%82%A3%E5%B9%B41987.2018.HD1080P.X264.AAC.Mandarin.CHS-ENG.Mp4Ba"
        },
        {
            "name": "\u90a3\u5e741987.2018.hd1080p.x2  .aac.manda  n.chs-eng",
            "action": "magnet:?xt=urn:btih:89e7b32f28ff9c8e432921506ada8e6db1dd90e2&dn=%E9%82%A3%E5%B9%B41987.2018.HD1080P.X264.AAC.Mandarin.CHS-ENG"
        },
        {
            "name": "\u90a3\u5e741987 hd 1080p mp4 2018   \u5927\u9646 \u5267\u60c5 \u7231\u60c5 \u4e2d\u6587\u5b57\u5e55",
            "action": "magnet:?xt=urn:btih:e3194f3f9df2930f500331f59da8073f8102e662&dn=%E9%82%A3%E5%B9%B41987%20HD%201080P%20MP4%202018%20%E4%B8%AD%E5%9B%BD%E5%A4%A7%E9%99%86%20%E5%89%A7%E6%83%85%20%E7%88%B1%E6%83%85%20%E4%B8%AD%E6%96%87%E5%AD%97%E5%B9%95"
        },
        {
            "name": "\u90a3\u5e741987.2018.hd1080p.x2  .aac.manda  n.chs-eng.mp4",
            "action": "magnet:?xt=urn:btih:83c51bb38858e8f6ae68ec1afd65304a6321e311&dn=%E9%82%A3%E5%B9%B41987.2018.HD1080P.X264.AAC.Mandarin.CHS-ENG.mp4"
        }
    ]
}