{
    "\u94bb\u77f3\u738b\u724c \u7b2c\u4e8c\u5b63": [
        {
            "name": "[\u5f02\u57df\u5b57\u5e55\u7ec4][\u94bb\u77f3\u738b\u724c\u7b2c\u4e8c\u5b63][ace of diamond s2][01-51_76-126][1280x720][\u7b80\u4f53]",
            "action": "magnet:?xt=urn:btih:64fbcae8458caf2bb4ac8f4d927fda524f4b788b&dn=%5B%E5%BC%82%E5%9F%9F%E5%AD%97%E5%B9%95%E7%BB%84%5D%5B%E9%92%BB%E7%9F%B3%E7%8E%8B%E7%89%8C%E7%AC%AC%E4%BA%8C%E5%AD%A3%5D%5BAce%20of%20Diamond%20S2%5D%5B01-51_76-126%5D%5B1280x720%5D%5B%E7%AE%80%E4%BD%93%5D"
        },
        {
            "name": "[\u5f02\u57df\u5b57\u5e55\u7ec4][\u94bb\u77f3\u738b\u724c\u7b2c\u4e8c\u5b63][ace of diamond s2][32_107][1280x720][\u7b80\u4f53].mp4",
            "action": "magnet:?xt=urn:btih:007bfefe646a71eb7d71256658a28bddffebf656&dn=%5B%E5%BC%82%E5%9F%9F%E5%AD%97%E5%B9%95%E7%BB%84%5D%5B%E9%92%BB%E7%9F%B3%E7%8E%8B%E7%89%8C%E7%AC%AC%E4%BA%8C%E5%AD%A3%5D%5BAce%20of%20Diamond%20S2%5D%5B32_107%5D%5B1280x720%5D%5B%E7%AE%80%E4%BD%93%5D.mp4"
        },
        {
            "name": "[\u5f02\u57df\u5b57\u5e55\u7ec4][\u94bb\u77f3\u738b\u724c\u7b2c\u4e8c\u5b63][ace of diamond s2][13_88][1280x720][\u7b80\u4f53].mp4",
            "action": "magnet:?xt=urn:btih:0d82951c528667414d2e52c4bdec692654b5d551&dn=%5B%E5%BC%82%E5%9F%9F%E5%AD%97%E5%B9%95%E7%BB%84%5D%5B%E9%92%BB%E7%9F%B3%E7%8E%8B%E7%89%8C%E7%AC%AC%E4%BA%8C%E5%AD%A3%5D%5BAce%20of%20Diamond%20S2%5D%5B13_88%5D%5B1280x720%5D%5B%E7%AE%80%E4%BD%93%5D.mp4"
        },
        {
            "name": "[\u5f02\u57df\u5b57\u5e55\u7ec4][\u94bb\u77f3\u738b\u724c\u7b2c\u4e8c\u5b63][ace of diamond s2][40_115][1280x720][\u7b80\u4f53].mp4",
            "action": "magnet:?xt=urn:btih:0d37166087c00e0c852310021c4de175dfa81487&dn=%5B%E5%BC%82%E5%9F%9F%E5%AD%97%E5%B9%95%E7%BB%84%5D%5B%E9%92%BB%E7%9F%B3%E7%8E%8B%E7%89%8C%E7%AC%AC%E4%BA%8C%E5%AD%A3%5D%5BAce%20of%20Diamond%20S2%5D%5B40_115%5D%5B1280x720%5D%5B%E7%AE%80%E4%BD%93%5D.mp4"
        },
        {
            "name": "[\u5f02\u57df\u5b57\u5e55\u7ec4][\u94bb\u77f3\u738b\u724c \u7b2c\u4e8c\u5b63][ace of diamond s2][02_77][720p][\u7b80\u4f53].mp4",
            "action": "magnet:?xt=urn:btih:0e86974f58adeb625d847d42314c00e632d773a2&dn=%5B%E5%BC%82%E5%9F%9F%E5%AD%97%E5%B9%95%E7%BB%84%5D%5B%E9%92%BB%E7%9F%B3%E7%8E%8B%E7%89%8C%20%E7%AC%AC%E4%BA%8C%E5%AD%A3%5D%5BAce%20of%20Diamond%20S2%5D%5B02_77%5D%5B720P%5D%5B%E7%AE%80%E4%BD%93%5D.mp4"
        },
        {
            "name": "[\u5f02\u57df\u5b57\u5e55\u7ec4][\u94bb\u77f3\u738b\u724c\u7b2c\u4e8c\u5b63][ace of diamond s2][48_123][1280x720][\u7b80\u4f53].mp4",
            "action": "magnet:?xt=urn:btih:120f3dd35e231fa78f12ed2f6cdc90d9626c0de2&dn=%5B%E5%BC%82%E5%9F%9F%E5%AD%97%E5%B9%95%E7%BB%84%5D%5B%E9%92%BB%E7%9F%B3%E7%8E%8B%E7%89%8C%E7%AC%AC%E4%BA%8C%E5%AD%A3%5D%5BAce%20of%20Diamond%20S2%5D%5B48_123%5D%5B1280x720%5D%5B%E7%AE%80%E4%BD%93%5D.mp4"
        },
        {
            "name": "[\u5f02\u57df\u5b57\u5e55\u7ec4][\u94bb\u77f3\u738b\u724c\u7b2c\u4e8c\u5b63][ace of diamond s2][34_109][1280x720][\u7b80\u4f53].mp4",
            "action": "magnet:?xt=urn:btih:2921bf675df8f09bf32b9b08e527e070af3d062c&dn=%5B%E5%BC%82%E5%9F%9F%E5%AD%97%E5%B9%95%E7%BB%84%5D%5B%E9%92%BB%E7%9F%B3%E7%8E%8B%E7%89%8C%E7%AC%AC%E4%BA%8C%E5%AD%A3%5D%5BAce%20of%20Diamond%20S2%5D%5B34_109%5D%5B1280x720%5D%5B%E7%AE%80%E4%BD%93%5D.mp4"
        },
        {
            "name": "[\u5f02\u57df\u5b57\u5e55\u7ec4][\u94bb\u77f3\u738b\u724c\u7b2c\u4e8c\u5b63][ace of diamond s2][12_87][1280x720][\u7b80\u4f53].mp4",
            "action": "magnet:?xt=urn:btih:2c90d6ca8297bafcd53296412437fdab91e443a5&dn=%5B%E5%BC%82%E5%9F%9F%E5%AD%97%E5%B9%95%E7%BB%84%5D%5B%E9%92%BB%E7%9F%B3%E7%8E%8B%E7%89%8C%E7%AC%AC%E4%BA%8C%E5%AD%A3%5D%5BAce%20of%20Diamond%20S2%5D%5B12_87%5D%5B1280x720%5D%5B%E7%AE%80%E4%BD%93%5D.mp4"
        },
        {
            "name": "[\u5f02\u57df\u5b57\u5e55\u7ec4][\u94bb\u77f3\u738b\u724c\u7b2c\u4e8c\u5b63][ace of diamond s2][11_86][1280x720][\u7b80\u4f53].mp4",
            "action": "magnet:?xt=urn:btih:3232ee08bc2a825c78957f155b3380e04c5acdd4&dn=%5B%E5%BC%82%E5%9F%9F%E5%AD%97%E5%B9%95%E7%BB%84%5D%5B%E9%92%BB%E7%9F%B3%E7%8E%8B%E7%89%8C%E7%AC%AC%E4%BA%8C%E5%AD%A3%5D%5BAce%20of%20Diamond%20S2%5D%5B11_86%5D%5B1280x720%5D%5B%E7%AE%80%E4%BD%93%5D.mp4"
        },
        {
            "name": "[\u5f02\u57df\u5b57\u5e55\u7ec4][\u94bb\u77f3\u738b\u724c\u7b2c\u4e8c\u5b63][ace of diamond s2][27_102][1280x720][\u7b80\u4f53].mp4",
            "action": "magnet:?xt=urn:btih:3db2d159a3ebabdea3f822f9bf776a357876da1a&dn=%5B%E5%BC%82%E5%9F%9F%E5%AD%97%E5%B9%95%E7%BB%84%5D%5B%E9%92%BB%E7%9F%B3%E7%8E%8B%E7%89%8C%E7%AC%AC%E4%BA%8C%E5%AD%A3%5D%5BAce%20of%20Diamond%20S2%5D%5B27_102%5D%5B1280x720%5D%5B%E7%AE%80%E4%BD%93%5D.mp4"
        },
        {
            "name": "[\u5f02\u57df\u5b57\u5e55\u7ec4][\u94bb\u77f3\u738b\u724c\u7b2c\u4e8c\u5b63][ace of diamond s2][20_95][1280x720][\u7b80\u4f53].mp4",
            "action": "magnet:?xt=urn:btih:3fcc90f193116e3312c3644fcb7eddce83abc560&dn=%5B%E5%BC%82%E5%9F%9F%E5%AD%97%E5%B9%95%E7%BB%84%5D%5B%E9%92%BB%E7%9F%B3%E7%8E%8B%E7%89%8C%E7%AC%AC%E4%BA%8C%E5%AD%A3%5D%5BAce%20of%20Diamond%20S2%5D%5B20_95%5D%5B1280x720%5D%5B%E7%AE%80%E4%BD%93%5D.mp4"
        },
        {
            "name": "[\u5f02\u57df\u5b57\u5e55\u7ec4][\u94bb\u77f3\u738b\u724c\u7b2c\u4e8c\u5b63][ace of diamond s2][49_124][1280x720][\u7b80\u4f53].mp4",
            "action": "magnet:?xt=urn:btih:3fc964bb8bb4f33ddb1b2b9c2eb074e32fba61ac&dn=%5B%E5%BC%82%E5%9F%9F%E5%AD%97%E5%B9%95%E7%BB%84%5D%5B%E9%92%BB%E7%9F%B3%E7%8E%8B%E7%89%8C%E7%AC%AC%E4%BA%8C%E5%AD%A3%5D%5BAce%20of%20Diamond%20S2%5D%5B49_124%5D%5B1280x720%5D%5B%E7%AE%80%E4%BD%93%5D.mp4"
        },
        {
            "name": "[\u5f02\u57df\u5b57\u5e55\u7ec4][\u94bb\u77f3\u738b\u724c\u7b2c\u4e8c\u5b63][ace of diamond s2][35_110][1280x720][\u7b80\u4f53].mp4",
            "action": "magnet:?xt=urn:btih:416fd8ecf93c9814b48f28986fcee4b4a7f74d1f&dn=%5B%E5%BC%82%E5%9F%9F%E5%AD%97%E5%B9%95%E7%BB%84%5D%5B%E9%92%BB%E7%9F%B3%E7%8E%8B%E7%89%8C%E7%AC%AC%E4%BA%8C%E5%AD%A3%5D%5BAce%20of%20Diamond%20S2%5D%5B35_110%5D%5B1280x720%5D%5B%E7%AE%80%E4%BD%93%5D.mp4"
        },
        {
            "name": "[\u5f02\u57df\u5b57\u5e55\u7ec4][\u94bb\u77f3\u738b\u724c\u7b2c\u4e8c\u5b63][ace of diamond s2][21_  ][1280x720][\u7b80\u4f53].mp4",
            "action": "magnet:?xt=urn:btih:430fe1056bf411a81ceacfde171c4c6d923f0c4e&dn=%5B%E5%BC%82%E5%9F%9F%E5%AD%97%E5%B9%95%E7%BB%84%5D%5B%E9%92%BB%E7%9F%B3%E7%8E%8B%E7%89%8C%E7%AC%AC%E4%BA%8C%E5%AD%A3%5D%5BAce%20of%20Diamond%20S2%5D%5B22_97%5D%5B1280x720%5D%5B%E7%AE%80%E4%BD%93%5D.mp4"
        },
        {
            "name": "[\u5f02\u57df\u5b57\u5e55\u7ec4][\u94bb\u77f3\u738b\u724c\u7b2c\u4e8c\u5b63][ace of diamond s2][22_97][1280x720][\u7b80\u4f53].mp4",
            "action": "magnet:?xt=urn:btih:451c3f1cc37c503f0672e9edf862be7805cc39d8&dn=%5B%E5%BC%82%E5%9F%9F%E5%AD%97%E5%B9%95%E7%BB%84%5D%5B%E9%92%BB%E7%9F%B3%E7%8E%8B%E7%89%8C%E7%AC%AC%E4%BA%8C%E5%AD%A3%5D%5BAce%20of%20Diamond%20S2%5D%5B30_105%5D%5B1280x720%5D%5B%E7%AE%80%E4%BD%93%5D.mp4"
        },
        {
            "name": "[\u5f02\u57df\u5b57\u5e55\u7ec4][\u94bb\u77f3\u738b\u724c\u7b2c\u4e8c\u5b63][ace of diamond s2][30_105][1280x720][\u7b80\u4f53].mp4",
            "action": "magnet:?xt=urn:btih:4ba960330b40f8b2d1059970d6cc69dc375c431d&dn=%5B%E5%BC%82%E5%9F%9F%E5%AD%97%E5%B9%95%E7%BB%84%5D%5B%E9%92%BB%E7%9F%B3%E7%8E%8B%E7%89%8C%20%E7%AC%AC%E4%BA%8C%E5%AD%A3%5D%5BAce%20of%20Diamond%20S2%5D%5B03_78%5D%5B720P%5D%5B%E7%AE%80%E4%BD%93%5D.mp4"
        },
        {
            "name": "[\u5f02\u57df\u5b57\u5e55\u7ec4][\u94bb\u77f3\u738b\u724c \u7b2c\u4e8c\u5b63][ace of diamond s2][03_78][720p][\u7b80\u4f53].mp4",
            "action": "magnet:?xt=urn:btih:507eeaa9a82e28b9b35d4f2c8d30de6c95186d9f&dn=%5B%E5%BC%82%E5%9F%9F%E5%AD%97%E5%B9%95%E7%BB%84%5D%5B%E9%92%BB%E7%9F%B3%E7%8E%8B%E7%89%8C%E7%AC%AC%E4%BA%8C%E5%AD%A3%5D%5BAce%20of%20Diamond%20S2%5D%5B28_103%5D%5B1280x720%5D%5B%E7%AE%80%E4%BD%93%5D.mp4"
        },
        {
            "name": "[\u5f02\u57df\u5b57\u5e55\u7ec4][\u94bb\u77f3\u738b\u724c\u7b2c\u4e8c\u5b63][ace of diamond s2][28_103][1280x720][\u7b80\u4f53].mp4",
            "action": "magnet:?xt=urn:btih:5070cca7746ad6054aeeb80e3a6e2c24fb14737b&dn=%5B%E5%BC%82%E5%9F%9F%E5%AD%97%E5%B9%95%E7%BB%84%5D%5B%E9%92%BB%E7%9F%B3%E7%8E%8B%E7%89%8C%E7%AC%AC%E4%BA%8C%E5%AD%A3%5D%5BAce%20of%20Diamond%20S2%5D%5B45_120%5D%5B1280x720%5D%5B%E7%AE%80%E4%BD%93%5D.mp4"
        },
        {
            "name": "[\u5f02\u57df\u5b57\u5e55\u7ec4][\u94bb\u77f3\u738b\u724c\u7b2c\u4e8c\u5b63][ace of diamond s2][45_120][1280x720][\u7b80\u4f53].mp4",
            "action": "magnet:?xt=urn:btih:516b4bed563eecbe307412e0558d050ec6328da6&dn=%5B%E5%BC%82%E5%9F%9F%E5%AD%97%E5%B9%95%E7%BB%84%5D%5B%E9%92%BB%E7%9F%B3%E7%8E%8B%E7%89%8C%E7%AC%AC%E4%BA%8C%E5%AD%A3%5D%5BAce%20of%20Diamond%20S2%5D%5B41_116%5D%5B1280x720%5D%5B%E7%AE%80%E4%BD%93%5D.mp4"
        }
    ]
}